{
  "restaurant": "LaScala's",
  "source_file": "dataset_K200.jsonl",
  "n_reviews": 200,
  "indexed_at": "2026-01-10T05:13:30.027146",
  "reviews": [
    {
      "idx": 0,
      "date": "2021-08-01 12:31:43",
      "stars": 3.0,
      "useful": 0,
      "text_hash": "fe6e615ed3c57af9",
      "task_relevance": {
        "G1a": {
          "keyword_match": false,
          "keywords_found": []
        }
      }
    },
    {
      "idx": 1,
      "date": "2020-11-03 00:26:06",
      "stars": 3.0,
      "useful": 0,
      "text_hash": "fbc086d9f8cb5955",
      "task_relevance": {
        "G1a": {
          "keyword_match": false,
          "keywords_found": []
        }
      }
    },
    {
      "idx": 2,
      "date": "2020-10-30 17:00:19",
      "stars": 5.0,
      "useful": 3,
      "text_hash": "bfeb9abf1a9d4cd2",
      "task_relevance": {
        "G1a": {
          "keyword_match": true,
          "keywords_found": [
            "accommodate"
          ]
        }
      }
    },
    {
      "idx": 3,
      "date": "2020-10-29 12:02:33",
      "stars": 5.0,
      "useful": 0,
      "text_hash": "145d96c4eac99cc1",
      "task_relevance": {
        "G1a": {
          "keyword_match": false,
          "keywords_found": []
        }
      }
    },
    {
      "idx": 4,
      "date": "2020-03-07 16:26:15",
      "stars": 5.0,
      "useful": 1,
      "text_hash": "97859609464ea67b",
      "task_relevance": {
        "G1a": {
          "keyword_match": false,
          "keywords_found": []
        }
      }
    },
    {
      "idx": 5,
      "date": "2020-02-15 21:40:26",
      "stars": 5.0,
      "useful": 0,
      "text_hash": "1e7dc63eb79c4095",
      "task_relevance": {
        "G1a": {
          "keyword_match": false,
          "keywords_found": []
        }
      }
    },
    {
      "idx": 6,
      "date": "2020-02-15 18:06:50",
      "stars": 5.0,
      "useful": 0,
      "text_hash": "2c225d9363f2301d",
      "task_relevance": {
        "G1a": {
          "keyword_match": true,
          "keywords_found": [
            "nut"
          ]
        }
      }
    },
    {
      "idx": 7,
      "date": "2020-02-15 18:04:14",
      "stars": 5.0,
      "useful": 0,
      "text_hash": "c3ed04f464c99cc2",
      "task_relevance": {
        "G1a": {
          "keyword_match": true,
          "keywords_found": [
            "nut"
          ]
        }
      }
    },
    {
      "idx": 8,
      "date": "2020-02-15 17:19:01",
      "stars": 4.0,
      "useful": 0,
      "text_hash": "2e14aac812e4525e",
      "task_relevance": {
        "G1a": {
          "keyword_match": false,
          "keywords_found": []
        }
      }
    },
    {
      "idx": 9,
      "date": "2020-02-11 03:22:16",
      "stars": 4.0,
      "useful": 1,
      "text_hash": "6d19d0189ed17849",
      "task_relevance": {
        "G1a": {
          "keyword_match": false,
          "keywords_found": []
        }
      }
    },
    {
      "idx": 10,
      "date": "2020-02-02 04:05:58",
      "stars": 2.0,
      "useful": 0,
      "text_hash": "f7b09d1de22d63f7",
      "task_relevance": {
        "G1a": {
          "keyword_match": false,
          "keywords_found": []
        }
      }
    },
    {
      "idx": 11,
      "date": "2020-01-20 07:53:06",
      "stars": 5.0,
      "useful": 0,
      "text_hash": "4647e2f69b595643",
      "task_relevance": {
        "G1a": {
          "keyword_match": false,
          "keywords_found": []
        }
      }
    },
    {
      "idx": 12,
      "date": "2020-01-02 23:42:01",
      "stars": 1.0,
      "useful": 0,
      "text_hash": "68513a98b362e3f1",
      "task_relevance": {
        "G1a": {
          "keyword_match": true,
          "keywords_found": [
            "sensitive"
          ]
        }
      }
    },
    {
      "idx": 13,
      "date": "2020-01-02 14:39:30",
      "stars": 4.0,
      "useful": 1,
      "text_hash": "ee4494b20b8c2270",
      "task_relevance": {
        "G1a": {
          "keyword_match": false,
          "keywords_found": []
        }
      }
    },
    {
      "idx": 14,
      "date": "2019-12-27 04:51:09",
      "stars": 5.0,
      "useful": 1,
      "text_hash": "e73b085abfce100c",
      "task_relevance": {
        "G1a": {
          "keyword_match": false,
          "keywords_found": []
        }
      }
    },
    {
      "idx": 15,
      "date": "2019-12-13 21:40:48",
      "stars": 5.0,
      "useful": 0,
      "text_hash": "f059d7f43889f64f",
      "task_relevance": {
        "G1a": {
          "keyword_match": false,
          "keywords_found": []
        }
      }
    },
    {
      "idx": 16,
      "date": "2019-11-06 04:15:40",
      "stars": 5.0,
      "useful": 0,
      "text_hash": "844d9156a24fa7b7",
      "task_relevance": {
        "G1a": {
          "keyword_match": false,
          "keywords_found": []
        }
      }
    },
    {
      "idx": 17,
      "date": "2019-10-25 20:46:38",
      "stars": 5.0,
      "useful": 0,
      "text_hash": "a2a593e502fff9fe",
      "task_relevance": {
        "G1a": {
          "keyword_match": false,
          "keywords_found": []
        }
      }
    },
    {
      "idx": 18,
      "date": "2019-09-08 04:54:30",
      "stars": 3.0,
      "useful": 0,
      "text_hash": "e21b5cea2497ab3d",
      "task_relevance": {
        "G1a": {
          "keyword_match": false,
          "keywords_found": []
        }
      }
    },
    {
      "idx": 19,
      "date": "2019-09-03 21:36:25",
      "stars": 3.0,
      "useful": 1,
      "text_hash": "dfb654f10a63f710",
      "task_relevance": {
        "G1a": {
          "keyword_match": false,
          "keywords_found": []
        }
      }
    },
    {
      "idx": 20,
      "date": "2019-09-01 01:33:15",
      "stars": 3.0,
      "useful": 1,
      "text_hash": "a3b38a6685a1c982",
      "task_relevance": {
        "G1a": {
          "keyword_match": false,
          "keywords_found": []
        }
      }
    },
    {
      "idx": 21,
      "date": "2019-08-21 11:40:58",
      "stars": 3.0,
      "useful": 0,
      "text_hash": "e756ceb574c9ad10",
      "task_relevance": {
        "G1a": {
          "keyword_match": false,
          "keywords_found": []
        }
      }
    },
    {
      "idx": 22,
      "date": "2019-08-07 09:01:04",
      "stars": 2.0,
      "useful": 0,
      "text_hash": "f80b0b3f44046742",
      "task_relevance": {
        "G1a": {
          "keyword_match": false,
          "keywords_found": []
        }
      }
    },
    {
      "idx": 23,
      "date": "2019-07-24 17:23:37",
      "stars": 5.0,
      "useful": 1,
      "text_hash": "af19c08411d39a16",
      "task_relevance": {
        "G1a": {
          "keyword_match": false,
          "keywords_found": []
        }
      }
    },
    {
      "idx": 24,
      "date": "2019-07-04 18:47:54",
      "stars": 3.0,
      "useful": 1,
      "text_hash": "90051ae8d04fb170",
      "task_relevance": {
        "G1a": {
          "keyword_match": false,
          "keywords_found": []
        }
      }
    },
    {
      "idx": 25,
      "date": "2019-07-03 03:58:33",
      "stars": 4.0,
      "useful": 2,
      "text_hash": "5cae87b18ac08717",
      "task_relevance": {
        "G1a": {
          "keyword_match": false,
          "keywords_found": []
        }
      }
    },
    {
      "idx": 26,
      "date": "2019-06-09 12:13:30",
      "stars": 2.0,
      "useful": 0,
      "text_hash": "b7c25f56c6e49327",
      "task_relevance": {
        "G1a": {
          "keyword_match": false,
          "keywords_found": []
        }
      }
    },
    {
      "idx": 27,
      "date": "2019-05-21 17:36:11",
      "stars": 2.0,
      "useful": 0,
      "text_hash": "899eb437c81e6cc2",
      "task_relevance": {
        "G1a": {
          "keyword_match": true,
          "keywords_found": [
            "nut"
          ]
        }
      }
    },
    {
      "idx": 28,
      "date": "2019-05-20 00:15:08",
      "stars": 4.0,
      "useful": 1,
      "text_hash": "91ebea0eb249a3d7",
      "task_relevance": {
        "G1a": {
          "keyword_match": false,
          "keywords_found": []
        }
      }
    },
    {
      "idx": 29,
      "date": "2019-05-19 00:56:15",
      "stars": 1.0,
      "useful": 0,
      "text_hash": "fdbfcf2d68f8cefe",
      "task_relevance": {
        "G1a": {
          "keyword_match": false,
          "keywords_found": []
        }
      }
    },
    {
      "idx": 30,
      "date": "2019-05-16 19:02:19",
      "stars": 5.0,
      "useful": 0,
      "text_hash": "8604f5f67257d9b2",
      "task_relevance": {
        "G1a": {
          "keyword_match": false,
          "keywords_found": []
        }
      }
    },
    {
      "idx": 31,
      "date": "2019-04-25 02:13:47",
      "stars": 4.0,
      "useful": 0,
      "text_hash": "1db9c98e50fccd9f",
      "task_relevance": {
        "G1a": {
          "keyword_match": false,
          "keywords_found": []
        }
      }
    },
    {
      "idx": 32,
      "date": "2019-04-22 16:40:50",
      "stars": 5.0,
      "useful": 1,
      "text_hash": "a5ca958c58c271e7",
      "task_relevance": {
        "G1a": {
          "keyword_match": false,
          "keywords_found": []
        }
      }
    },
    {
      "idx": 33,
      "date": "2019-04-21 19:02:16",
      "stars": 5.0,
      "useful": 0,
      "text_hash": "920eb3f0a7704109",
      "task_relevance": {
        "G1a": {
          "keyword_match": false,
          "keywords_found": []
        }
      }
    },
    {
      "idx": 34,
      "date": "2019-04-09 20:21:43",
      "stars": 5.0,
      "useful": 3,
      "text_hash": "d0b94de79c3946ab",
      "task_relevance": {
        "G1a": {
          "keyword_match": false,
          "keywords_found": []
        }
      }
    },
    {
      "idx": 35,
      "date": "2019-04-09 02:08:55",
      "stars": 4.0,
      "useful": 2,
      "text_hash": "06a6662b97932525",
      "task_relevance": {
        "G1a": {
          "keyword_match": false,
          "keywords_found": []
        }
      }
    },
    {
      "idx": 36,
      "date": "2019-03-29 17:44:07",
      "stars": 1.0,
      "useful": 0,
      "text_hash": "d9cd41b4eda8f0f0",
      "task_relevance": {
        "G1a": {
          "keyword_match": false,
          "keywords_found": []
        }
      }
    },
    {
      "idx": 37,
      "date": "2019-03-24 00:18:44",
      "stars": 5.0,
      "useful": 0,
      "text_hash": "b57127c12513d2f7",
      "task_relevance": {
        "G1a": {
          "keyword_match": false,
          "keywords_found": []
        }
      }
    },
    {
      "idx": 38,
      "date": "2019-03-20 16:07:14",
      "stars": 1.0,
      "useful": 0,
      "text_hash": "bcca3cb1f6547b15",
      "task_relevance": {
        "G1a": {
          "keyword_match": false,
          "keywords_found": []
        }
      }
    },
    {
      "idx": 39,
      "date": "2019-02-17 11:13:55",
      "stars": 4.0,
      "useful": 1,
      "text_hash": "32ac7fa1a695f9b0",
      "task_relevance": {
        "G1a": {
          "keyword_match": false,
          "keywords_found": []
        }
      }
    },
    {
      "idx": 40,
      "date": "2019-02-10 01:08:00",
      "stars": 1.0,
      "useful": 2,
      "text_hash": "5c0864f827b0d94c",
      "task_relevance": {
        "G1a": {
          "keyword_match": false,
          "keywords_found": []
        }
      }
    },
    {
      "idx": 41,
      "date": "2019-02-04 15:38:29",
      "stars": 4.0,
      "useful": 0,
      "text_hash": "1173ea766b47b6ec",
      "task_relevance": {
        "G1a": {
          "keyword_match": false,
          "keywords_found": []
        }
      }
    },
    {
      "idx": 42,
      "date": "2019-01-17 14:33:50",
      "stars": 5.0,
      "useful": 0,
      "text_hash": "51bfaa2ec2cf1a86",
      "task_relevance": {
        "G1a": {
          "keyword_match": false,
          "keywords_found": []
        }
      }
    },
    {
      "idx": 43,
      "date": "2019-01-14 02:26:23",
      "stars": 4.0,
      "useful": 3,
      "text_hash": "2573bc2455e9ba91",
      "task_relevance": {
        "G1a": {
          "keyword_match": false,
          "keywords_found": []
        }
      }
    },
    {
      "idx": 44,
      "date": "2018-12-30 03:25:00",
      "stars": 1.0,
      "useful": 0,
      "text_hash": "7f36db305473843a",
      "task_relevance": {
        "G1a": {
          "keyword_match": false,
          "keywords_found": []
        }
      }
    },
    {
      "idx": 45,
      "date": "2018-12-25 14:53:54",
      "stars": 5.0,
      "useful": 0,
      "text_hash": "5f70650416972170",
      "task_relevance": {
        "G1a": {
          "keyword_match": false,
          "keywords_found": []
        }
      }
    },
    {
      "idx": 46,
      "date": "2018-12-25 12:59:18",
      "stars": 2.0,
      "useful": 0,
      "text_hash": "ed3d1d8e8736b438",
      "task_relevance": {
        "G1a": {
          "keyword_match": false,
          "keywords_found": []
        }
      }
    },
    {
      "idx": 47,
      "date": "2018-11-09 17:13:20",
      "stars": 5.0,
      "useful": 0,
      "text_hash": "386e20a2e3c97312",
      "task_relevance": {
        "G1a": {
          "keyword_match": false,
          "keywords_found": []
        }
      }
    },
    {
      "idx": 48,
      "date": "2018-11-06 02:04:32",
      "stars": 1.0,
      "useful": 0,
      "text_hash": "6e409a9e46a9241a",
      "task_relevance": {
        "G1a": {
          "keyword_match": false,
          "keywords_found": []
        }
      }
    },
    {
      "idx": 49,
      "date": "2018-11-05 17:53:27",
      "stars": 3.0,
      "useful": 2,
      "text_hash": "cc7130717d666872",
      "task_relevance": {
        "G1a": {
          "keyword_match": false,
          "keywords_found": []
        }
      }
    },
    {
      "idx": 50,
      "date": "2018-10-18 23:27:03",
      "stars": 3.0,
      "useful": 1,
      "text_hash": "1c572b9d07a6d9b6",
      "task_relevance": {
        "G1a": {
          "keyword_match": false,
          "keywords_found": []
        }
      }
    },
    {
      "idx": 51,
      "date": "2018-10-14 16:45:40",
      "stars": 4.0,
      "useful": 0,
      "text_hash": "8759d49c4111ea80",
      "task_relevance": {
        "G1a": {
          "keyword_match": false,
          "keywords_found": []
        }
      }
    },
    {
      "idx": 52,
      "date": "2018-10-13 01:22:03",
      "stars": 2.0,
      "useful": 0,
      "text_hash": "6bad545cfae93c47",
      "task_relevance": {
        "G1a": {
          "keyword_match": false,
          "keywords_found": []
        }
      }
    },
    {
      "idx": 53,
      "date": "2018-09-27 18:25:45",
      "stars": 4.0,
      "useful": 0,
      "text_hash": "3df5346b1156da6c",
      "task_relevance": {
        "G1a": {
          "keyword_match": false,
          "keywords_found": []
        }
      }
    },
    {
      "idx": 54,
      "date": "2018-09-21 23:21:21",
      "stars": 3.0,
      "useful": 0,
      "text_hash": "5135a262766c1adc",
      "task_relevance": {
        "G1a": {
          "keyword_match": false,
          "keywords_found": []
        }
      }
    },
    {
      "idx": 55,
      "date": "2018-09-17 21:54:50",
      "stars": 3.0,
      "useful": 0,
      "text_hash": "72ade23972a59c4a",
      "task_relevance": {
        "G1a": {
          "keyword_match": false,
          "keywords_found": []
        }
      }
    },
    {
      "idx": 56,
      "date": "2018-09-17 17:54:58",
      "stars": 3.0,
      "useful": 0,
      "text_hash": "c2d6016c43b8150f",
      "task_relevance": {
        "G1a": {
          "keyword_match": false,
          "keywords_found": []
        }
      }
    },
    {
      "idx": 57,
      "date": "2018-09-13 01:29:17",
      "stars": 1.0,
      "useful": 0,
      "text_hash": "f123d4ad29a38cfd",
      "task_relevance": {
        "G1a": {
          "keyword_match": false,
          "keywords_found": []
        }
      }
    },
    {
      "idx": 58,
      "date": "2018-08-19 19:06:15",
      "stars": 4.0,
      "useful": 0,
      "text_hash": "83236817f1360228",
      "task_relevance": {
        "G1a": {
          "keyword_match": false,
          "keywords_found": []
        }
      }
    },
    {
      "idx": 59,
      "date": "2018-08-17 22:50:50",
      "stars": 5.0,
      "useful": 0,
      "text_hash": "c4d18fe01c8251eb",
      "task_relevance": {
        "G1a": {
          "keyword_match": false,
          "keywords_found": []
        }
      }
    },
    {
      "idx": 60,
      "date": "2018-08-07 22:02:42",
      "stars": 4.0,
      "useful": 3,
      "text_hash": "215c4eca0e8cbb14",
      "task_relevance": {
        "G1a": {
          "keyword_match": false,
          "keywords_found": []
        }
      }
    },
    {
      "idx": 61,
      "date": "2018-07-25 20:00:22",
      "stars": 5.0,
      "useful": 1,
      "text_hash": "68fc83cdf717ad5c",
      "task_relevance": {
        "G1a": {
          "keyword_match": false,
          "keywords_found": []
        }
      }
    },
    {
      "idx": 62,
      "date": "2018-07-25 00:18:19",
      "stars": 2.0,
      "useful": 3,
      "text_hash": "453e09e231de0dcb",
      "task_relevance": {
        "G1a": {
          "keyword_match": false,
          "keywords_found": []
        }
      }
    },
    {
      "idx": 63,
      "date": "2018-07-22 22:48:05",
      "stars": 5.0,
      "useful": 0,
      "text_hash": "db4731141d654b1f",
      "task_relevance": {
        "G1a": {
          "keyword_match": false,
          "keywords_found": []
        }
      }
    },
    {
      "idx": 64,
      "date": "2018-07-18 21:54:49",
      "stars": 1.0,
      "useful": 0,
      "text_hash": "7b4a7a7332d196ba",
      "task_relevance": {
        "G1a": {
          "keyword_match": false,
          "keywords_found": []
        }
      }
    },
    {
      "idx": 65,
      "date": "2018-07-08 15:29:55",
      "stars": 5.0,
      "useful": 6,
      "text_hash": "201974f99090bdd4",
      "task_relevance": {
        "G1a": {
          "keyword_match": false,
          "keywords_found": []
        }
      }
    },
    {
      "idx": 66,
      "date": "2018-07-08 05:22:06",
      "stars": 2.0,
      "useful": 0,
      "text_hash": "97cb4be0355e5383",
      "task_relevance": {
        "G1a": {
          "keyword_match": true,
          "keywords_found": [
            "nut"
          ]
        }
      }
    },
    {
      "idx": 67,
      "date": "2018-07-07 19:42:15",
      "stars": 5.0,
      "useful": 0,
      "text_hash": "3cbb3a95fba25cdd",
      "task_relevance": {
        "G1a": {
          "keyword_match": false,
          "keywords_found": []
        }
      }
    },
    {
      "idx": 68,
      "date": "2018-06-24 16:03:46",
      "stars": 5.0,
      "useful": 0,
      "text_hash": "6944a6f24523f835",
      "task_relevance": {
        "G1a": {
          "keyword_match": false,
          "keywords_found": []
        }
      }
    },
    {
      "idx": 69,
      "date": "2018-06-23 21:33:32",
      "stars": 1.0,
      "useful": 1,
      "text_hash": "d3408555158c7998",
      "task_relevance": {
        "G1a": {
          "keyword_match": false,
          "keywords_found": []
        }
      }
    },
    {
      "idx": 70,
      "date": "2018-06-19 23:41:52",
      "stars": 4.0,
      "useful": 1,
      "text_hash": "6e701fc5910dc330",
      "task_relevance": {
        "G1a": {
          "keyword_match": false,
          "keywords_found": []
        }
      }
    },
    {
      "idx": 71,
      "date": "2018-06-14 20:33:41",
      "stars": 1.0,
      "useful": 0,
      "text_hash": "adabdf49717a20b9",
      "task_relevance": {
        "G1a": {
          "keyword_match": false,
          "keywords_found": []
        }
      }
    },
    {
      "idx": 72,
      "date": "2018-06-13 23:00:31",
      "stars": 5.0,
      "useful": 0,
      "text_hash": "5b861a2618970868",
      "task_relevance": {
        "G1a": {
          "keyword_match": true,
          "keywords_found": [
            "nut",
            "nuts"
          ]
        }
      }
    },
    {
      "idx": 73,
      "date": "2018-05-23 22:39:30",
      "stars": 5.0,
      "useful": 0,
      "text_hash": "1166840f5b08f1e0",
      "task_relevance": {
        "G1a": {
          "keyword_match": false,
          "keywords_found": []
        }
      }
    },
    {
      "idx": 74,
      "date": "2018-05-22 17:07:09",
      "stars": 5.0,
      "useful": 0,
      "text_hash": "c6e29e6bfcb08af2",
      "task_relevance": {
        "G1a": {
          "keyword_match": false,
          "keywords_found": []
        }
      }
    },
    {
      "idx": 75,
      "date": "2018-05-22 01:25:27",
      "stars": 3.0,
      "useful": 0,
      "text_hash": "4a4ff225aadd4ecf",
      "task_relevance": {
        "G1a": {
          "keyword_match": false,
          "keywords_found": []
        }
      }
    },
    {
      "idx": 76,
      "date": "2018-05-14 23:01:04",
      "stars": 4.0,
      "useful": 0,
      "text_hash": "6a336de7bbb743a1",
      "task_relevance": {
        "G1a": {
          "keyword_match": false,
          "keywords_found": []
        }
      }
    },
    {
      "idx": 77,
      "date": "2018-05-01 14:01:44",
      "stars": 4.0,
      "useful": 3,
      "text_hash": "9eb95ec81902d7a1",
      "task_relevance": {
        "G1a": {
          "keyword_match": false,
          "keywords_found": []
        }
      }
    },
    {
      "idx": 78,
      "date": "2018-04-28 20:45:02",
      "stars": 5.0,
      "useful": 1,
      "text_hash": "cfb7831fa327c4f9",
      "task_relevance": {
        "G1a": {
          "keyword_match": false,
          "keywords_found": []
        }
      }
    },
    {
      "idx": 79,
      "date": "2018-04-23 17:24:39",
      "stars": 1.0,
      "useful": 2,
      "text_hash": "9636a319331dfd77",
      "task_relevance": {
        "G1a": {
          "keyword_match": false,
          "keywords_found": []
        }
      }
    },
    {
      "idx": 80,
      "date": "2018-04-18 19:27:11",
      "stars": 5.0,
      "useful": 0,
      "text_hash": "a41785e71a940a36",
      "task_relevance": {
        "G1a": {
          "keyword_match": false,
          "keywords_found": []
        }
      }
    },
    {
      "idx": 81,
      "date": "2018-04-17 19:18:27",
      "stars": 2.0,
      "useful": 1,
      "text_hash": "2eb5306121576642",
      "task_relevance": {
        "G1a": {
          "keyword_match": true,
          "keywords_found": [
            "nut"
          ]
        }
      }
    },
    {
      "idx": 82,
      "date": "2018-04-16 17:31:55",
      "stars": 5.0,
      "useful": 0,
      "text_hash": "d780968152655b43",
      "task_relevance": {
        "G1a": {
          "keyword_match": false,
          "keywords_found": []
        }
      }
    },
    {
      "idx": 83,
      "date": "2018-04-09 01:20:41",
      "stars": 3.0,
      "useful": 0,
      "text_hash": "6825124be80f3cc4",
      "task_relevance": {
        "G1a": {
          "keyword_match": false,
          "keywords_found": []
        }
      }
    },
    {
      "idx": 84,
      "date": "2018-04-04 00:08:05",
      "stars": 4.0,
      "useful": 0,
      "text_hash": "4edbdaad3b925e8f",
      "task_relevance": {
        "G1a": {
          "keyword_match": false,
          "keywords_found": []
        }
      }
    },
    {
      "idx": 85,
      "date": "2018-03-25 11:40:56",
      "stars": 3.0,
      "useful": 0,
      "text_hash": "598a774b92850aa9",
      "task_relevance": {
        "G1a": {
          "keyword_match": false,
          "keywords_found": []
        }
      }
    },
    {
      "idx": 86,
      "date": "2018-03-13 17:52:23",
      "stars": 5.0,
      "useful": 0,
      "text_hash": "8143f6b044f72ec9",
      "task_relevance": {
        "G1a": {
          "keyword_match": false,
          "keywords_found": []
        }
      }
    },
    {
      "idx": 87,
      "date": "2018-03-12 17:57:41",
      "stars": 5.0,
      "useful": 0,
      "text_hash": "cbb361582c8d4f07",
      "task_relevance": {
        "G1a": {
          "keyword_match": false,
          "keywords_found": []
        }
      }
    },
    {
      "idx": 88,
      "date": "2018-03-09 00:36:25",
      "stars": 4.0,
      "useful": 0,
      "text_hash": "62791405b0b218f6",
      "task_relevance": {
        "G1a": {
          "keyword_match": false,
          "keywords_found": []
        }
      }
    },
    {
      "idx": 89,
      "date": "2018-03-01 01:04:58",
      "stars": 1.0,
      "useful": 5,
      "text_hash": "a81800b280df1aa2",
      "task_relevance": {
        "G1a": {
          "keyword_match": true,
          "keywords_found": [
            "nut"
          ]
        }
      }
    },
    {
      "idx": 90,
      "date": "2018-02-19 23:29:28",
      "stars": 5.0,
      "useful": 1,
      "text_hash": "678be6680f9e8677",
      "task_relevance": {
        "G1a": {
          "keyword_match": true,
          "keywords_found": [
            "nut"
          ]
        }
      }
    },
    {
      "idx": 91,
      "date": "2018-02-19 22:27:44",
      "stars": 3.0,
      "useful": 0,
      "text_hash": "f5cf3debef89ce83",
      "task_relevance": {
        "G1a": {
          "keyword_match": false,
          "keywords_found": []
        }
      }
    },
    {
      "idx": 92,
      "date": "2018-02-18 04:37:49",
      "stars": 3.0,
      "useful": 0,
      "text_hash": "348d493c88e20400",
      "task_relevance": {
        "G1a": {
          "keyword_match": false,
          "keywords_found": []
        }
      }
    },
    {
      "idx": 93,
      "date": "2018-02-08 03:52:11",
      "stars": 5.0,
      "useful": 7,
      "text_hash": "0ec38ec853580a00",
      "task_relevance": {
        "G1a": {
          "keyword_match": false,
          "keywords_found": []
        }
      }
    },
    {
      "idx": 94,
      "date": "2018-01-30 21:21:03",
      "stars": 1.0,
      "useful": 0,
      "text_hash": "2f74e0929933c740",
      "task_relevance": {
        "G1a": {
          "keyword_match": true,
          "keywords_found": [
            "nut"
          ]
        }
      }
    },
    {
      "idx": 95,
      "date": "2018-01-28 21:21:27",
      "stars": 1.0,
      "useful": 1,
      "text_hash": "b97e75ade42866b8",
      "task_relevance": {
        "G1a": {
          "keyword_match": true,
          "keywords_found": [
            "nut"
          ]
        }
      }
    },
    {
      "idx": 96,
      "date": "2018-01-28 00:33:38",
      "stars": 4.0,
      "useful": 1,
      "text_hash": "3bd762090dc61b8b",
      "task_relevance": {
        "G1a": {
          "keyword_match": true,
          "keywords_found": [
            "nut",
            "nuts",
            "walnut"
          ]
        }
      }
    },
    {
      "idx": 97,
      "date": "2018-01-26 04:17:40",
      "stars": 3.0,
      "useful": 0,
      "text_hash": "b287e33af9624ba2",
      "task_relevance": {
        "G1a": {
          "keyword_match": false,
          "keywords_found": []
        }
      }
    },
    {
      "idx": 98,
      "date": "2018-01-22 17:59:48",
      "stars": 5.0,
      "useful": 0,
      "text_hash": "217a841c06975675",
      "task_relevance": {
        "G1a": {
          "keyword_match": false,
          "keywords_found": []
        }
      }
    },
    {
      "idx": 99,
      "date": "2018-01-20 19:55:43",
      "stars": 1.0,
      "useful": 0,
      "text_hash": "531e256c9c50ef71",
      "task_relevance": {
        "G1a": {
          "keyword_match": false,
          "keywords_found": []
        }
      }
    },
    {
      "idx": 100,
      "date": "2018-01-18 23:10:02",
      "stars": 1.0,
      "useful": 0,
      "text_hash": "7aeeff2eb4dca970",
      "task_relevance": {
        "G1a": {
          "keyword_match": false,
          "keywords_found": []
        }
      }
    },
    {
      "idx": 101,
      "date": "2018-01-17 00:31:35",
      "stars": 3.0,
      "useful": 0,
      "text_hash": "309365daa2613058",
      "task_relevance": {
        "G1a": {
          "keyword_match": false,
          "keywords_found": []
        }
      }
    },
    {
      "idx": 102,
      "date": "2018-01-14 23:59:55",
      "stars": 4.0,
      "useful": 0,
      "text_hash": "3e0fa1488ca42462",
      "task_relevance": {
        "G1a": {
          "keyword_match": false,
          "keywords_found": []
        }
      }
    },
    {
      "idx": 103,
      "date": "2018-01-06 02:44:53",
      "stars": 2.0,
      "useful": 0,
      "text_hash": "23d61e582b342a1a",
      "task_relevance": {
        "G1a": {
          "keyword_match": false,
          "keywords_found": []
        }
      }
    },
    {
      "idx": 104,
      "date": "2017-12-28 11:25:36",
      "stars": 5.0,
      "useful": 0,
      "text_hash": "134fbb391e946fe3",
      "task_relevance": {
        "G1a": {
          "keyword_match": false,
          "keywords_found": []
        }
      }
    },
    {
      "idx": 105,
      "date": "2017-12-27 22:41:03",
      "stars": 1.0,
      "useful": 1,
      "text_hash": "5bf9662e755ef7c4",
      "task_relevance": {
        "G1a": {
          "keyword_match": false,
          "keywords_found": []
        }
      }
    },
    {
      "idx": 106,
      "date": "2017-12-08 22:40:08",
      "stars": 1.0,
      "useful": 1,
      "text_hash": "29e8d8c10718b9ba",
      "task_relevance": {
        "G1a": {
          "keyword_match": false,
          "keywords_found": []
        }
      }
    },
    {
      "idx": 107,
      "date": "2017-11-29 16:21:07",
      "stars": 3.0,
      "useful": 0,
      "text_hash": "0b3fb7bcb57296b6",
      "task_relevance": {
        "G1a": {
          "keyword_match": false,
          "keywords_found": []
        }
      }
    },
    {
      "idx": 108,
      "date": "2017-11-21 04:11:04",
      "stars": 5.0,
      "useful": 0,
      "text_hash": "2da93f94c36edfab",
      "task_relevance": {
        "G1a": {
          "keyword_match": false,
          "keywords_found": []
        }
      }
    },
    {
      "idx": 109,
      "date": "2017-11-13 02:54:34",
      "stars": 4.0,
      "useful": 5,
      "text_hash": "32152f12be93224a",
      "task_relevance": {
        "G1a": {
          "keyword_match": false,
          "keywords_found": []
        }
      }
    },
    {
      "idx": 110,
      "date": "2017-11-13 02:45:29",
      "stars": 4.0,
      "useful": 2,
      "text_hash": "f9a9259be5894993",
      "task_relevance": {
        "G1a": {
          "keyword_match": false,
          "keywords_found": []
        }
      }
    },
    {
      "idx": 111,
      "date": "2017-11-04 12:09:32",
      "stars": 3.0,
      "useful": 0,
      "text_hash": "1354144b6fe63cdb",
      "task_relevance": {
        "G1a": {
          "keyword_match": false,
          "keywords_found": []
        }
      }
    },
    {
      "idx": 112,
      "date": "2017-10-30 22:54:09",
      "stars": 4.0,
      "useful": 0,
      "text_hash": "96710a926e41a8d7",
      "task_relevance": {
        "G1a": {
          "keyword_match": false,
          "keywords_found": []
        }
      }
    },
    {
      "idx": 113,
      "date": "2017-09-30 04:29:06",
      "stars": 2.0,
      "useful": 0,
      "text_hash": "7c0d9faec9ea5408",
      "task_relevance": {
        "G1a": {
          "keyword_match": false,
          "keywords_found": []
        }
      }
    },
    {
      "idx": 114,
      "date": "2017-09-17 02:34:05",
      "stars": 5.0,
      "useful": 0,
      "text_hash": "e3a9bade9e7ff125",
      "task_relevance": {
        "G1a": {
          "keyword_match": false,
          "keywords_found": []
        }
      }
    },
    {
      "idx": 115,
      "date": "2017-09-11 14:32:44",
      "stars": 3.0,
      "useful": 0,
      "text_hash": "0d51d0cee2508555",
      "task_relevance": {
        "G1a": {
          "keyword_match": false,
          "keywords_found": []
        }
      }
    },
    {
      "idx": 116,
      "date": "2017-09-07 19:29:35",
      "stars": 4.0,
      "useful": 0,
      "text_hash": "4d43d9580fcc038a",
      "task_relevance": {
        "G1a": {
          "keyword_match": true,
          "keywords_found": [
            "nut"
          ]
        }
      }
    },
    {
      "idx": 117,
      "date": "2017-08-14 02:00:31",
      "stars": 4.0,
      "useful": 0,
      "text_hash": "4d12533d5f6959ca",
      "task_relevance": {
        "G1a": {
          "keyword_match": false,
          "keywords_found": []
        }
      }
    },
    {
      "idx": 118,
      "date": "2017-08-07 16:54:21",
      "stars": 2.0,
      "useful": 1,
      "text_hash": "81c34d1a6d31dede",
      "task_relevance": {
        "G1a": {
          "keyword_match": false,
          "keywords_found": []
        }
      }
    },
    {
      "idx": 119,
      "date": "2017-08-02 20:56:32",
      "stars": 4.0,
      "useful": 0,
      "text_hash": "d409890bfb44eb11",
      "task_relevance": {
        "G1a": {
          "keyword_match": false,
          "keywords_found": []
        }
      }
    },
    {
      "idx": 120,
      "date": "2017-07-30 00:03:34",
      "stars": 5.0,
      "useful": 1,
      "text_hash": "12ac3ca011ea6e2f",
      "task_relevance": {
        "G1a": {
          "keyword_match": false,
          "keywords_found": []
        }
      }
    },
    {
      "idx": 121,
      "date": "2017-07-24 23:32:49",
      "stars": 4.0,
      "useful": 0,
      "text_hash": "f2573977ad16e1f4",
      "task_relevance": {
        "G1a": {
          "keyword_match": false,
          "keywords_found": []
        }
      }
    },
    {
      "idx": 122,
      "date": "2017-07-18 20:43:17",
      "stars": 3.0,
      "useful": 0,
      "text_hash": "77196e5db957c153",
      "task_relevance": {
        "G1a": {
          "keyword_match": true,
          "keywords_found": [
            "nut"
          ]
        }
      }
    },
    {
      "idx": 123,
      "date": "2017-06-28 15:56:01",
      "stars": 3.0,
      "useful": 0,
      "text_hash": "f8e24bef1911e106",
      "task_relevance": {
        "G1a": {
          "keyword_match": false,
          "keywords_found": []
        }
      }
    },
    {
      "idx": 124,
      "date": "2017-06-28 14:15:35",
      "stars": 3.0,
      "useful": 0,
      "text_hash": "ad6b136375527df8",
      "task_relevance": {
        "G1a": {
          "keyword_match": false,
          "keywords_found": []
        }
      }
    },
    {
      "idx": 125,
      "date": "2017-06-07 14:01:15",
      "stars": 5.0,
      "useful": 1,
      "text_hash": "c4866b5f63b898d9",
      "task_relevance": {
        "G1a": {
          "keyword_match": false,
          "keywords_found": []
        }
      }
    },
    {
      "idx": 126,
      "date": "2017-06-01 23:04:17",
      "stars": 1.0,
      "useful": 1,
      "text_hash": "0081aca7a11f5059",
      "task_relevance": {
        "G1a": {
          "keyword_match": true,
          "keywords_found": [
            "nut"
          ]
        }
      }
    },
    {
      "idx": 127,
      "date": "2017-05-29 14:01:36",
      "stars": 1.0,
      "useful": 1,
      "text_hash": "e2c7484c927c2bd8",
      "task_relevance": {
        "G1a": {
          "keyword_match": false,
          "keywords_found": []
        }
      }
    },
    {
      "idx": 128,
      "date": "2017-05-16 17:26:47",
      "stars": 4.0,
      "useful": 1,
      "text_hash": "c564e3a63c7f43fe",
      "task_relevance": {
        "G1a": {
          "keyword_match": false,
          "keywords_found": []
        }
      }
    },
    {
      "idx": 129,
      "date": "2017-04-22 21:06:47",
      "stars": 5.0,
      "useful": 2,
      "text_hash": "2b03c173b062ae01",
      "task_relevance": {
        "G1a": {
          "keyword_match": false,
          "keywords_found": []
        }
      }
    },
    {
      "idx": 130,
      "date": "2017-03-23 00:44:57",
      "stars": 5.0,
      "useful": 2,
      "text_hash": "c4133ddaa647140a",
      "task_relevance": {
        "G1a": {
          "keyword_match": false,
          "keywords_found": []
        }
      }
    },
    {
      "idx": 131,
      "date": "2017-03-05 18:12:33",
      "stars": 4.0,
      "useful": 0,
      "text_hash": "07db6aa45d5d607e",
      "task_relevance": {
        "G1a": {
          "keyword_match": false,
          "keywords_found": []
        }
      }
    },
    {
      "idx": 132,
      "date": "2017-02-27 03:40:19",
      "stars": 4.0,
      "useful": 4,
      "text_hash": "c6ae57d8cbe0ac9f",
      "task_relevance": {
        "G1a": {
          "keyword_match": false,
          "keywords_found": []
        }
      }
    },
    {
      "idx": 133,
      "date": "2017-02-26 03:29:51",
      "stars": 4.0,
      "useful": 0,
      "text_hash": "8a074cfd020b76d9",
      "task_relevance": {
        "G1a": {
          "keyword_match": true,
          "keywords_found": [
            "accommodating"
          ]
        }
      }
    },
    {
      "idx": 134,
      "date": "2017-02-23 22:39:24",
      "stars": 5.0,
      "useful": 1,
      "text_hash": "c7bc26ec7bd29131",
      "task_relevance": {
        "G1a": {
          "keyword_match": false,
          "keywords_found": []
        }
      }
    },
    {
      "idx": 135,
      "date": "2017-02-20 01:12:01",
      "stars": 5.0,
      "useful": 0,
      "text_hash": "7f2a5fe7542f08c5",
      "task_relevance": {
        "G1a": {
          "keyword_match": false,
          "keywords_found": []
        }
      }
    },
    {
      "idx": 136,
      "date": "2017-02-07 12:39:41",
      "stars": 4.0,
      "useful": 0,
      "text_hash": "aac9d3a81533efe7",
      "task_relevance": {
        "G1a": {
          "keyword_match": false,
          "keywords_found": []
        }
      }
    },
    {
      "idx": 137,
      "date": "2017-02-03 03:25:00",
      "stars": 3.0,
      "useful": 0,
      "text_hash": "b2fc67837753140d",
      "task_relevance": {
        "G1a": {
          "keyword_match": false,
          "keywords_found": []
        }
      }
    },
    {
      "idx": 138,
      "date": "2017-01-31 00:15:26",
      "stars": 5.0,
      "useful": 0,
      "text_hash": "6ee021938acea7dd",
      "task_relevance": {
        "G1a": {
          "keyword_match": false,
          "keywords_found": []
        }
      }
    },
    {
      "idx": 139,
      "date": "2017-01-25 01:57:20",
      "stars": 4.0,
      "useful": 0,
      "text_hash": "2c2c8a195cd29925",
      "task_relevance": {
        "G1a": {
          "keyword_match": false,
          "keywords_found": []
        }
      }
    },
    {
      "idx": 140,
      "date": "2017-01-17 05:19:47",
      "stars": 4.0,
      "useful": 0,
      "text_hash": "cfeec08f5337f6f3",
      "task_relevance": {
        "G1a": {
          "keyword_match": false,
          "keywords_found": []
        }
      }
    },
    {
      "idx": 141,
      "date": "2016-12-31 02:13:59",
      "stars": 5.0,
      "useful": 0,
      "text_hash": "2505ac9865f6b153",
      "task_relevance": {
        "G1a": {
          "keyword_match": false,
          "keywords_found": []
        }
      }
    },
    {
      "idx": 142,
      "date": "2016-12-22 03:38:18",
      "stars": 5.0,
      "useful": 0,
      "text_hash": "daaebd238d7a20da",
      "task_relevance": {
        "G1a": {
          "keyword_match": true,
          "keywords_found": [
            "gluten"
          ]
        }
      }
    },
    {
      "idx": 143,
      "date": "2016-11-25 23:37:32",
      "stars": 1.0,
      "useful": 2,
      "text_hash": "8fd3ccf86263721c",
      "task_relevance": {
        "G1a": {
          "keyword_match": false,
          "keywords_found": []
        }
      }
    },
    {
      "idx": 144,
      "date": "2016-11-20 16:45:13",
      "stars": 4.0,
      "useful": 0,
      "text_hash": "8ba9f5a23b41dae5",
      "task_relevance": {
        "G1a": {
          "keyword_match": false,
          "keywords_found": []
        }
      }
    },
    {
      "idx": 145,
      "date": "2016-11-18 23:21:55",
      "stars": 1.0,
      "useful": 2,
      "text_hash": "3c2f164a93924d1a",
      "task_relevance": {
        "G1a": {
          "keyword_match": true,
          "keywords_found": [
            "accommodate",
            "accommodated"
          ]
        }
      }
    },
    {
      "idx": 146,
      "date": "2016-11-15 02:07:04",
      "stars": 1.0,
      "useful": 2,
      "text_hash": "1a90fa00ddc838d1",
      "task_relevance": {
        "G1a": {
          "keyword_match": true,
          "keywords_found": [
            "nut"
          ]
        }
      }
    },
    {
      "idx": 147,
      "date": "2016-11-13 02:35:50",
      "stars": 1.0,
      "useful": 1,
      "text_hash": "89113332ff410c46",
      "task_relevance": {
        "G1a": {
          "keyword_match": true,
          "keywords_found": [
            "nut"
          ]
        }
      }
    },
    {
      "idx": 148,
      "date": "2016-11-01 19:20:10",
      "stars": 1.0,
      "useful": 1,
      "text_hash": "ef78e17e60be49b9",
      "task_relevance": {
        "G1a": {
          "keyword_match": false,
          "keywords_found": []
        }
      }
    },
    {
      "idx": 149,
      "date": "2016-10-31 17:45:53",
      "stars": 3.0,
      "useful": 2,
      "text_hash": "387112dd59b9f9e5",
      "task_relevance": {
        "G1a": {
          "keyword_match": false,
          "keywords_found": []
        }
      }
    },
    {
      "idx": 150,
      "date": "2016-10-21 16:10:15",
      "stars": 5.0,
      "useful": 2,
      "text_hash": "ded4528312edbab9",
      "task_relevance": {
        "G1a": {
          "keyword_match": false,
          "keywords_found": []
        }
      }
    },
    {
      "idx": 151,
      "date": "2016-09-29 13:58:50",
      "stars": 4.0,
      "useful": 0,
      "text_hash": "7a9f3000ace5c7b4",
      "task_relevance": {
        "G1a": {
          "keyword_match": true,
          "keywords_found": [
            "nut"
          ]
        }
      }
    },
    {
      "idx": 152,
      "date": "2016-09-25 20:17:06",
      "stars": 4.0,
      "useful": 0,
      "text_hash": "f998e8155f6875d0",
      "task_relevance": {
        "G1a": {
          "keyword_match": false,
          "keywords_found": []
        }
      }
    },
    {
      "idx": 153,
      "date": "2016-09-23 05:06:58",
      "stars": 4.0,
      "useful": 2,
      "text_hash": "4c8407d7d973ffcf",
      "task_relevance": {
        "G1a": {
          "keyword_match": false,
          "keywords_found": []
        }
      }
    },
    {
      "idx": 154,
      "date": "2016-09-15 01:37:55",
      "stars": 3.0,
      "useful": 0,
      "text_hash": "09da1a81a0b11f7c",
      "task_relevance": {
        "G1a": {
          "keyword_match": false,
          "keywords_found": []
        }
      }
    },
    {
      "idx": 155,
      "date": "2016-09-03 19:08:57",
      "stars": 4.0,
      "useful": 0,
      "text_hash": "30a492926c388ed9",
      "task_relevance": {
        "G1a": {
          "keyword_match": false,
          "keywords_found": []
        }
      }
    },
    {
      "idx": 156,
      "date": "2016-08-24 14:55:26",
      "stars": 5.0,
      "useful": 3,
      "text_hash": "e13d0c11403aeae4",
      "task_relevance": {
        "G1a": {
          "keyword_match": true,
          "keywords_found": [
            "nut"
          ]
        }
      }
    },
    {
      "idx": 157,
      "date": "2016-08-16 01:56:28",
      "stars": 4.0,
      "useful": 0,
      "text_hash": "b5cc77bfbfee6b39",
      "task_relevance": {
        "G1a": {
          "keyword_match": false,
          "keywords_found": []
        }
      }
    },
    {
      "idx": 158,
      "date": "2016-07-27 19:40:47",
      "stars": 5.0,
      "useful": 0,
      "text_hash": "8b27add472a67cd8",
      "task_relevance": {
        "G1a": {
          "keyword_match": false,
          "keywords_found": []
        }
      }
    },
    {
      "idx": 159,
      "date": "2016-07-22 14:01:46",
      "stars": 4.0,
      "useful": 2,
      "text_hash": "9554d540bf90ab0b",
      "task_relevance": {
        "G1a": {
          "keyword_match": false,
          "keywords_found": []
        }
      }
    },
    {
      "idx": 160,
      "date": "2016-06-23 00:19:38",
      "stars": 1.0,
      "useful": 1,
      "text_hash": "8a34bd5fec238594",
      "task_relevance": {
        "G1a": {
          "keyword_match": false,
          "keywords_found": []
        }
      }
    },
    {
      "idx": 161,
      "date": "2016-06-12 20:46:42",
      "stars": 5.0,
      "useful": 0,
      "text_hash": "d2819c6817690ed5",
      "task_relevance": {
        "G1a": {
          "keyword_match": false,
          "keywords_found": []
        }
      }
    },
    {
      "idx": 162,
      "date": "2016-06-05 23:04:51",
      "stars": 5.0,
      "useful": 4,
      "text_hash": "1cfa0965d9d39329",
      "task_relevance": {
        "G1a": {
          "keyword_match": false,
          "keywords_found": []
        }
      }
    },
    {
      "idx": 163,
      "date": "2016-06-04 23:24:50",
      "stars": 4.0,
      "useful": 2,
      "text_hash": "7e9a92ff074c4415",
      "task_relevance": {
        "G1a": {
          "keyword_match": false,
          "keywords_found": []
        }
      }
    },
    {
      "idx": 164,
      "date": "2016-05-14 16:27:30",
      "stars": 5.0,
      "useful": 0,
      "text_hash": "d86fab7fd566cdc0",
      "task_relevance": {
        "G1a": {
          "keyword_match": false,
          "keywords_found": []
        }
      }
    },
    {
      "idx": 165,
      "date": "2016-05-08 14:39:36",
      "stars": 4.0,
      "useful": 2,
      "text_hash": "8ff568b4ea27506b",
      "task_relevance": {
        "G1a": {
          "keyword_match": true,
          "keywords_found": [
            "nut"
          ]
        }
      }
    },
    {
      "idx": 166,
      "date": "2016-04-29 14:44:10",
      "stars": 4.0,
      "useful": 0,
      "text_hash": "58f3151cba71cb33",
      "task_relevance": {
        "G1a": {
          "keyword_match": true,
          "keywords_found": [
            "accommodating"
          ]
        }
      }
    },
    {
      "idx": 167,
      "date": "2016-04-19 20:02:25",
      "stars": 4.0,
      "useful": 0,
      "text_hash": "8fb2e9cf51f39249",
      "task_relevance": {
        "G1a": {
          "keyword_match": false,
          "keywords_found": []
        }
      }
    },
    {
      "idx": 168,
      "date": "2016-04-08 03:34:39",
      "stars": 5.0,
      "useful": 0,
      "text_hash": "7216afa6a174130d",
      "task_relevance": {
        "G1a": {
          "keyword_match": false,
          "keywords_found": []
        }
      }
    },
    {
      "idx": 169,
      "date": "2016-03-30 23:45:07",
      "stars": 5.0,
      "useful": 0,
      "text_hash": "86704ba6adba81a0",
      "task_relevance": {
        "G1a": {
          "keyword_match": false,
          "keywords_found": []
        }
      }
    },
    {
      "idx": 170,
      "date": "2016-03-30 08:48:54",
      "stars": 5.0,
      "useful": 0,
      "text_hash": "1badff6f0ab341b3",
      "task_relevance": {
        "G1a": {
          "keyword_match": false,
          "keywords_found": []
        }
      }
    },
    {
      "idx": 171,
      "date": "2016-03-25 18:46:52",
      "stars": 5.0,
      "useful": 0,
      "text_hash": "43e396dfab98c85b",
      "task_relevance": {
        "G1a": {
          "keyword_match": false,
          "keywords_found": []
        }
      }
    },
    {
      "idx": 172,
      "date": "2016-03-04 21:36:58",
      "stars": 2.0,
      "useful": 1,
      "text_hash": "b2d471a588c2ed10",
      "task_relevance": {
        "G1a": {
          "keyword_match": false,
          "keywords_found": []
        }
      }
    },
    {
      "idx": 173,
      "date": "2016-02-21 04:39:00",
      "stars": 5.0,
      "useful": 2,
      "text_hash": "91bd653742f0d84c",
      "task_relevance": {
        "G1a": {
          "keyword_match": true,
          "keywords_found": [
            "nut"
          ]
        }
      }
    },
    {
      "idx": 174,
      "date": "2016-02-15 20:01:18",
      "stars": 5.0,
      "useful": 0,
      "text_hash": "42d4d6af3811db9a",
      "task_relevance": {
        "G1a": {
          "keyword_match": false,
          "keywords_found": []
        }
      }
    },
    {
      "idx": 175,
      "date": "2016-02-15 17:25:41",
      "stars": 4.0,
      "useful": 1,
      "text_hash": "8ced524ed9cb12ad",
      "task_relevance": {
        "G1a": {
          "keyword_match": false,
          "keywords_found": []
        }
      }
    },
    {
      "idx": 176,
      "date": "2016-02-06 03:47:51",
      "stars": 4.0,
      "useful": 0,
      "text_hash": "9999916cdbb1d019",
      "task_relevance": {
        "G1a": {
          "keyword_match": false,
          "keywords_found": []
        }
      }
    },
    {
      "idx": 177,
      "date": "2016-01-30 16:21:24",
      "stars": 4.0,
      "useful": 2,
      "text_hash": "b5e2d4b720a42348",
      "task_relevance": {
        "G1a": {
          "keyword_match": false,
          "keywords_found": []
        }
      }
    },
    {
      "idx": 178,
      "date": "2016-01-19 02:33:18",
      "stars": 5.0,
      "useful": 0,
      "text_hash": "ff062dfb3d2927ed",
      "task_relevance": {
        "G1a": {
          "keyword_match": false,
          "keywords_found": []
        }
      }
    },
    {
      "idx": 179,
      "date": "2016-01-02 01:56:26",
      "stars": 3.0,
      "useful": 0,
      "text_hash": "c0c8fee415409613",
      "task_relevance": {
        "G1a": {
          "keyword_match": false,
          "keywords_found": []
        }
      }
    },
    {
      "idx": 180,
      "date": "2016-01-01 19:17:11",
      "stars": 1.0,
      "useful": 1,
      "text_hash": "d39cb1aea29fc5f1",
      "task_relevance": {
        "G1a": {
          "keyword_match": false,
          "keywords_found": []
        }
      }
    },
    {
      "idx": 181,
      "date": "2015-12-08 16:34:49",
      "stars": 3.0,
      "useful": 0,
      "text_hash": "bc21cd9e7420ae30",
      "task_relevance": {
        "G1a": {
          "keyword_match": false,
          "keywords_found": []
        }
      }
    },
    {
      "idx": 182,
      "date": "2015-12-06 00:59:20",
      "stars": 4.0,
      "useful": 0,
      "text_hash": "945f6dea94d5daae",
      "task_relevance": {
        "G1a": {
          "keyword_match": false,
          "keywords_found": []
        }
      }
    },
    {
      "idx": 183,
      "date": "2015-11-28 21:31:13",
      "stars": 2.0,
      "useful": 2,
      "text_hash": "dc2cfb54bb3720e8",
      "task_relevance": {
        "G1a": {
          "keyword_match": true,
          "keywords_found": [
            "nut",
            "safe",
            "warning"
          ]
        }
      }
    },
    {
      "idx": 184,
      "date": "2015-11-23 16:13:39",
      "stars": 1.0,
      "useful": 2,
      "text_hash": "50bd0c2542bca93e",
      "task_relevance": {
        "G1a": {
          "keyword_match": true,
          "keywords_found": [
            "nut"
          ]
        }
      }
    },
    {
      "idx": 185,
      "date": "2015-11-22 03:09:06",
      "stars": 2.0,
      "useful": 0,
      "text_hash": "5d306b44e0491dfe",
      "task_relevance": {
        "G1a": {
          "keyword_match": true,
          "keywords_found": [
            "accommodating"
          ]
        }
      }
    },
    {
      "idx": 186,
      "date": "2015-11-08 17:28:25",
      "stars": 5.0,
      "useful": 0,
      "text_hash": "762e65f669a4fea9",
      "task_relevance": {
        "G1a": {
          "keyword_match": true,
          "keywords_found": [
            "nut"
          ]
        }
      }
    },
    {
      "idx": 187,
      "date": "2015-10-19 10:53:44",
      "stars": 3.0,
      "useful": 0,
      "text_hash": "c345225d9152669f",
      "task_relevance": {
        "G1a": {
          "keyword_match": false,
          "keywords_found": []
        }
      }
    },
    {
      "idx": 188,
      "date": "2015-10-18 15:22:05",
      "stars": 1.0,
      "useful": 0,
      "text_hash": "47b6ec098a893ebf",
      "task_relevance": {
        "G1a": {
          "keyword_match": true,
          "keywords_found": [
            "nut"
          ]
        }
      }
    },
    {
      "idx": 189,
      "date": "2015-10-14 22:01:45",
      "stars": 5.0,
      "useful": 0,
      "text_hash": "11b4c6a8f72b33ff",
      "task_relevance": {
        "G1a": {
          "keyword_match": false,
          "keywords_found": []
        }
      }
    },
    {
      "idx": 190,
      "date": "2015-10-09 16:24:49",
      "stars": 2.0,
      "useful": 0,
      "text_hash": "cf2eb60f9b1de068",
      "task_relevance": {
        "G1a": {
          "keyword_match": false,
          "keywords_found": []
        }
      }
    },
    {
      "idx": 191,
      "date": "2015-10-08 21:30:26",
      "stars": 5.0,
      "useful": 3,
      "text_hash": "b7e0186ab30db349",
      "task_relevance": {
        "G1a": {
          "keyword_match": false,
          "keywords_found": []
        }
      }
    },
    {
      "idx": 192,
      "date": "2015-09-29 22:57:31",
      "stars": 4.0,
      "useful": 0,
      "text_hash": "6361d7532a3651ba",
      "task_relevance": {
        "G1a": {
          "keyword_match": false,
          "keywords_found": []
        }
      }
    },
    {
      "idx": 193,
      "date": "2015-09-21 15:08:56",
      "stars": 3.0,
      "useful": 0,
      "text_hash": "6af20a4589b118cd",
      "task_relevance": {
        "G1a": {
          "keyword_match": false,
          "keywords_found": []
        }
      }
    },
    {
      "idx": 194,
      "date": "2015-09-12 16:24:39",
      "stars": 4.0,
      "useful": 1,
      "text_hash": "b3a9c83de4551798",
      "task_relevance": {
        "G1a": {
          "keyword_match": false,
          "keywords_found": []
        }
      }
    },
    {
      "idx": 195,
      "date": "2015-09-04 20:59:22",
      "stars": 2.0,
      "useful": 1,
      "text_hash": "74a8cb2dcf4a9097",
      "task_relevance": {
        "G1a": {
          "keyword_match": false,
          "keywords_found": []
        }
      }
    },
    {
      "idx": 196,
      "date": "2015-08-26 01:11:56",
      "stars": 5.0,
      "useful": 0,
      "text_hash": "83575bcb8aad3ca5",
      "task_relevance": {
        "G1a": {
          "keyword_match": false,
          "keywords_found": []
        }
      }
    },
    {
      "idx": 197,
      "date": "2015-08-25 23:18:34",
      "stars": 5.0,
      "useful": 0,
      "text_hash": "84a88387f2b2c6fd",
      "task_relevance": {
        "G1a": {
          "keyword_match": true,
          "keywords_found": [
            "peanut",
            "nut"
          ]
        }
      }
    },
    {
      "idx": 198,
      "date": "2015-08-23 01:03:37",
      "stars": 3.0,
      "useful": 0,
      "text_hash": "7c1f2a70dfcc2a22",
      "task_relevance": {
        "G1a": {
          "keyword_match": false,
          "keywords_found": []
        }
      }
    },
    {
      "idx": 199,
      "date": "2015-08-22 14:59:34",
      "stars": 4.0,
      "useful": 0,
      "text_hash": "e59fbb358e23b585",
      "task_relevance": {
        "G1a": {
          "keyword_match": false,
          "keywords_found": []
        }
      }
    }
  ]
}